bml_ocr/__init__.py
bml_ocr/extract.py
bml_ocr/receipt_model.py
bml_ocr-0.1.1.dist-info/LICENSE
bml_ocr-0.1.1.dist-info/METADATA
bml_ocr-0.1.1.dist-info/WHEEL
bml_ocr-0.1.1.dist-info/RECORD
