Metadata-Version: 2.1
Name: bml-ocr
Version: 0.1.1
Summary: A package to extract details from BML transfer receipts.
License: MIT
Author: Naffah Abdulla Rasheed
Author-email: mail@naffah.me
Requires-Python: >=3.11,<4.0
Classifier: License :: OSI Approved :: MIT License
Classifier: Programming Language :: Python :: 3
Classifier: Programming Language :: Python :: 3.11
Classifier: Programming Language :: Python :: 3.12
Requires-Dist: easyocr (>=1.7.1,<2.0.0)
Requires-Dist: python-levenshtein (>=0.25.1,<0.26.0)
Requires-Dist: torch (>=2.3.0,<3.0.0)
Requires-Dist: torchaudio (>=2.3.0,<3.0.0)
Requires-Dist: torchvision (>=0.18.0,<0.19.0)
